compylex/__init__.py
compylex/compiler.py
compylex-1.1.dist-info/LICENSE
compylex-1.1.dist-info/METADATA
compylex-1.1.dist-info/WHEEL
compylex-1.1.dist-info/top_level.txt
compylex-1.1.dist-info/RECORD
