Metadata-Version: 2.1
Name: compylex
Version: 1.1
Summary: Code compiler
Home-page: https://github.com/AshiqAbdulkhader/Compylex
Author: Muhammed Ashiq Abdul Khader
Author-email: ashiqabdulkhader@gmail.com
License: MIT License
Platform: UNKNOWN
